{
  "tests": [
    {
      "name": "test_default_conversion",
      "setup": "sudo -H pip3 install -r requirements.txt",
      "run": "pytest -v  -k \"test_default_conversion\"",
      "input": "",
      "output": "",
      "comparison": "included",
      "timeout": 10,
      "points": 1
    },
    {
      "name": "test_specific_conversion",
      "setup": "sudo -H pip3 install -r requirements.txt",
      "run": "pytest -v  -k \"test_specific_conversion\"",
      "input": "",
      "output": "",
      "comparison": "included",
      "timeout": 10,
      "points": 1
    },
    {
      "name": "test_conversion_with_string_units",
      "setup": "sudo -H pip3 install -r requirements.txt",
      "run": "pytest -v  -k \"test_conversion_with_string_units\"",
      "input": "",
      "output": "",
      "comparison": "included",
      "timeout": 10,
      "points": 1
    },
    {
      "name": "test_reverse_conversion",
      "setup": "sudo -H pip3 install -r requirements.txt",
      "run": "pytest -v  -k \"test_reverse_conversion\"",
      "input": "",
      "output": "",
      "comparison": "included",
      "timeout": 10,
      "points": 1
    },
    {
      "name": "test_division_normal",
      "setup": "sudo -H pip3 install -r requirements.txt",
      "run": "pytest -v  -k \"test_division_normal\"",
      "input": "",
      "output": "",
      "comparison": "included",
      "timeout": 10,
      "points": 1
    },
    {
      "name": "test_division_zero_remainder",
      "setup": "sudo -H pip3 install -r requirements.txt",
      "run": "pytest -v  -k \"test_division_zero_remainder\"",
      "input": "",
      "output": "",
      "comparison": "included",
      "timeout": 10,
      "points": 1
    },
    {
      "name": "test_division_by_zero",
      "setup": "sudo -H pip3 install -r requirements.txt",
      "run": "pytest -v  -k \"test_division_by_zero\"",
      "input": "",
      "output": "",
      "comparison": "included",
      "timeout": 10,
      "points": 1
    }
  ]
}